sprockets.mixins.mediatype-3.0.4-py3.8-nspkg.pth
sprockets/mixins/mediatype/__init__.py
sprockets/mixins/mediatype/content.py
sprockets/mixins/mediatype/handlers.py
sprockets/mixins/mediatype/transcoders.py
sprockets.mixins.mediatype-3.0.4.dist-info/LICENSE
sprockets.mixins.mediatype-3.0.4.dist-info/METADATA
sprockets.mixins.mediatype-3.0.4.dist-info/WHEEL
sprockets.mixins.mediatype-3.0.4.dist-info/namespace_packages.txt
sprockets.mixins.mediatype-3.0.4.dist-info/top_level.txt
sprockets.mixins.mediatype-3.0.4.dist-info/RECORD
