Metadata-Version: 2.1
Name: sprockets.mixins.mediatype
Version: 3.0.4
Summary: A mixin for reporting handling content-type/accept headers
Home-page: https://github.com/sprockets/sprockets.mixins.mediatype
Author: AWeber Communications
Author-email: api@aweber.com
License: BSD
Platform: UNKNOWN
Classifier: Development Status :: 5 - Production/Stable
Classifier: Intended Audience :: Developers
Classifier: License :: OSI Approved :: BSD License
Classifier: Natural Language :: English
Classifier: Operating System :: OS Independent
Classifier: Programming Language :: Python :: 3
Classifier: Programming Language :: Python :: 3.7
Classifier: Programming Language :: Python :: 3.8
Classifier: Programming Language :: Python :: 3.9
Classifier: Programming Language :: Python :: Implementation :: CPython
Classifier: Topic :: Software Development :: Libraries
Classifier: Topic :: Software Development :: Libraries :: Python Modules
Requires-Python: >=3.7
Requires-Dist: ietfparse (<2,>=1.5.1)
Requires-Dist: tornado (<7,>=5)
Provides-Extra: msgpack
Requires-Dist: u-msgpack-python (<3,>=2.5.0) ; extra == 'msgpack'
